<?xml version="1.0" encoding="utf-8"?><index><stem n="recombin"><phr n="recombinant"><ent r="3" t="2" w="239" /><ent r="4" t="2" w="296" /><ent r="4" t="2" w="301" /><ent r="4" t="2" w="306" /><ent r="3" t="9" w="517" /><ent r="3" t="9" w="792" /><ent r="3" t="9" w="797" /><ent r="3" t="9" w="1273" /><ent r="3" t="9" w="1279" /><ent r="3" t="9" w="1654" /><ent r="3" t="9" w="1668" /><ent r="3" t="9" w="1918" /><ent r="3" t="33" w="93" /><ent r="3" t="35" w="584" /><ent r="3" t="35" w="627" /><ent r="3" t="35" w="686" /><ent r="3" t="35" w="843" /><ent r="3" t="35" w="864" /><ent r="3" t="35" w="891" /><ent r="3" t="35" w="927" /><ent r="3" t="36" w="1092" /><ent r="3" t="36" w="1218" /><ent r="3" t="40" w="139" /><ent r="3" t="83" w="51" /><ent r="3" t="83" w="57" /><ent r="3" t="83" w="387" /><ent r="3" t="83" w="499" /><ent r="3" t="83" w="503" /><ent r="3" t="83" w="586" /><ent r="3" t="83" w="689" /><ent r="3" t="83" w="742" /><ent r="3" t="85" w="43" /><ent r="3" t="93" w="1677" /><ent r="1000" t="98" w="11" /><ent r="102" t="98" w="29" /><ent r="1000" t="113" w="12" /><ent r="102" t="113" w="35" /><ent r="3" t="116" w="46" /><ent r="3" t="116" w="53" /></phr><phr n="Recombinant"><ent r="82" t="9" w="779" /><ent r="82" t="9" w="1204" /><ent r="82" t="9" w="1260" /><ent r="82" t="9" w="1640" /><ent r="72" t="83" w="379" /><ent r="72" t="83" w="680" /></phr><phr n="recombinants"><ent r="3" t="83" w="534" /><ent r="3" t="93" w="1327" /><ent r="3" t="93" w="1791" /></phr><phr n="recombination"><ent r="3" t="83" w="544" /></phr></stem><stem n="mice"><phr n="mice"><ent r="3" t="2" w="241" /><ent r="4" t="2" w="298" /><ent r="4" t="2" w="308" /><ent r="3" t="9" w="519" /><ent r="3" t="9" w="617" /><ent r="3" t="9" w="794" /><ent r="3" t="9" w="1276" /><ent r="3" t="9" w="1331" /><ent r="3" t="9" w="1347" /><ent r="3" t="31" w="187" /><ent r="3" t="31" w="198" /><ent r="3" t="33" w="95" /><ent r="3" t="40" w="121" /><ent r="3" t="58" w="291" /><ent r="3" t="58" w="304" /><ent r="3" t="83" w="53" /><ent r="4" t="85" w="61" /><ent r="3" t="93" w="11" /><ent r="1000" t="113" w="16" /><ent r="102" t="113" w="39" /></phr><phr n="Mice"><ent r="82" t="9" w="606" /><ent r="82" t="9" w="781" /><ent r="82" t="9" w="1208" /><ent r="82" t="9" w="1262" /><ent r="3" t="9" w="1450" /><ent r="3" t="31" w="2591" /><ent r="5" t="83" w="111" /><ent r="5" t="83" w="125" /><ent r="72" t="83" w="381" /><ent r="3" t="93" w="763" /><ent r="5" t="98" w="44" /></phr></stem><stem n="rat"><phr n="rat"><ent r="3" t="2" w="243" /><ent r="3" t="9" w="1712" /><ent r="3" t="9" w="1715" /><ent r="3" t="9" w="1749" /><ent r="3" t="9" w="2019" /><ent r="3" t="9" w="2062" /><ent r="3" t="9" w="2103" /><ent r="64" t="9" w="2171" /><ent r="4" t="9" w="2428" /><ent r="3" t="31" w="2564" /><ent r="3" t="31" w="2624" /><ent r="3" t="33" w="97" /><ent r="3" t="35" w="688" /><ent r="3" t="35" w="893" /><ent r="3" t="35" w="929" /><ent r="3" t="36" w="1094" /><ent r="3" t="36" w="1220" /><ent r="3" t="57" w="339" /><ent r="3" t="57" w="453" /><ent r="5" t="60" w="745" /><ent r="3" t="72" w="143" /><ent r="3" t="81" w="76" /><ent r="3" t="93" w="1467" /><ent r="3" t="93" w="1508" /><ent r="64" t="93" w="1576" /><ent r="4" t="93" w="1936" /><ent r="3" t="106" w="91" /><ent r="3" t="106" w="104" /><ent r="3" t="116" w="55" /></phr><phr n="rats"><ent r="4" t="2" w="303" /><ent r="3" t="9" w="521" /><ent r="3" t="9" w="1656" /><ent r="3" t="9" w="1701" /><ent r="3" t="83" w="59" /><ent r="4" t="85" w="57" /><ent r="3" t="93" w="13" /><ent r="3" t="93" w="1255" /><ent r="1000" t="113" w="18" /><ent r="102" t="113" w="41" /></phr><phr n="Rats"><ent r="82" t="9" w="1642" /><ent r="5" t="83" w="118" /><ent r="72" t="83" w="682" /></phr><phr n="Rat"><ent r="3" t="9" w="1662" /><ent r="3" t="9" w="1933" /><ent r="3" t="9" w="2026" /><ent r="6" t="13" w="289" /><ent r="3" t="31" w="2535" /><ent r="3" t="31" w="2646" /><ent r="3" t="31" w="2832" /><ent r="3" t="35" w="647" /><ent r="3" t="35" w="742" /><ent r="3" t="35" w="898" /><ent r="3" t="36" w="1126" /><ent r="5" t="58" w="118" /><ent r="92" t="93" w="1054" /><ent r="92" t="93" w="1060" /><ent r="3" t="93" w="1087" /><ent r="92" t="93" w="1385" /><ent r="92" t="93" w="1395" /><ent r="3" t="93" w="1438" /><ent r="5" t="106" w="134" /></phr></stem><stem n="strain"><phr n="strains"><ent r="3" t="2" w="244" /><ent r="3" t="9" w="513" /><ent r="3" t="9" w="621" /><ent r="3" t="9" w="720" /><ent r="3" t="9" w="799" /><ent r="3" t="9" w="804" /><ent r="3" t="9" w="912" /><ent r="3" t="9" w="990" /><ent r="3" t="9" w="1005" /><ent r="3" t="9" w="1115" /><ent r="3" t="9" w="1232" /><ent r="3" t="9" w="1281" /><ent r="3" t="9" w="1298" /><ent r="3" t="9" w="1445" /><ent r="3" t="9" w="1670" /><ent r="3" t="9" w="1674" /><ent r="3" t="9" w="1956" /><ent r="3" t="9" w="1960" /><ent r="3" t="9" w="1972" /><ent r="3" t="9" w="2096" /><ent r="3" t="9" w="2134" /><ent r="3" t="26" w="153" /><ent r="3" t="31" w="201" /><ent r="3" t="31" w="2586" /><ent r="3" t="31" w="2680" /><ent r="3" t="33" w="98" /><ent r="3" t="35" w="568" /><ent r="3" t="35" w="589" /><ent r="3" t="40" w="141" /><ent r="3" t="40" w="176" /><ent r="4" t="44" w="283" /><ent r="3" t="44" w="520" /><ent r="3" t="83" w="468" /><ent r="3" t="83" w="484" /><ent r="3" t="83" w="496" /><ent r="3" t="83" w="588" /><ent r="3" t="83" w="666" /><ent r="3" t="83" w="670" /><ent r="3" t="83" w="713" /><ent r="3" t="83" w="784" /><ent r="3" t="83" w="788" /><ent r="3" t="83" w="923" /><ent r="3" t="83" w="984" /><ent r="3" t="93" w="18" /><ent r="3" t="93" w="101" /><ent r="3" t="93" w="228" /><ent r="3" t="93" w="233" /><ent r="3" t="93" w="405" /><ent r="3" t="93" w="492" /><ent r="3" t="93" w="515" /><ent r="3" t="93" w="520" /><ent r="3" t="93" w="584" /><ent r="3" t="93" w="593" /><ent r="3" t="93" w="636" /><ent r="3" t="93" w="694" /><ent r="3" t="93" w="758" /><ent r="3" t="93" w="900" /><ent r="3" t="93" w="975" /><ent r="3" t="93" w="1019" /><ent r="3" t="93" w="1078" /><ent r="3" t="93" w="1083" /><ent r="3" t="93" w="1294" /><ent r="3" t="93" w="1303" /><ent r="3" t="93" w="1314" /><ent r="3" t="93" w="1338" /><ent r="3" t="93" w="1420" /><ent r="3" t="93" w="1424" /><ent r="3" t="93" w="1434" /><ent r="3" t="93" w="1501" /><ent r="3" t="93" w="1539" /><ent r="3" t="93" w="1657" /><ent r="3" t="93" w="1679" /><ent r="3" t="93" w="1758" /><ent r="3" t="93" w="1767" /><ent r="3" t="93" w="1778" /><ent r="3" t="93" w="1802" /><ent r="4" t="98" w="91" /><ent r="1000" t="113" w="14" /><ent r="102" t="113" w="37" /><ent r="4" t="113" w="90" /><ent r="3" t="116" w="49" /><ent r="3" t="116" w="56" /></phr><phr n="strain"><ent r="3" t="9" w="623" /><ent r="3" t="9" w="811" /><ent r="3" t="9" w="1132" /><ent r="3" t="9" w="1283" /><ent r="3" t="9" w="1293" /><ent r="3" t="9" w="1303" /><ent r="3" t="9" w="1686" /><ent r="3" t="9" w="1704" /><ent r="3" t="9" w="1974" /><ent r="3" t="9" w="2098" /><ent r="3" t="9" w="2106" /><ent r="6" t="13" w="319" /><ent r="4" t="14" w="95" /><ent r="3" t="26" w="203" /><ent r="3" t="26" w="212" /><ent r="3" t="31" w="2641" /><ent r="3" t="31" w="2648" /><ent r="3" t="39" w="1414" /><ent r="3" t="40" w="219" /><ent r="3" t="40" w="227" /><ent r="3" t="44" w="186" /><ent r="3" t="44" w="199" /><ent r="3" t="44" w="201" /><ent r="3" t="44" w="207" /><ent r="4" t="44" w="293" /><ent r="4" t="44" w="303" /><ent r="3" t="83" w="338" /><ent r="3" t="83" w="356" /><ent r="3" t="83" w="363" /><ent r="3" t="83" w="524" /><ent r="3" t="83" w="727" /><ent r="3" t="83" w="736" /><ent r="3" t="83" w="744" /><ent r="3" t="83" w="898" /><ent r="3" t="83" w="915" /><ent r="3" t="83" w="942" /><ent r="3" t="83" w="952" /><ent r="3" t="83" w="966" /><ent r="3" t="83" w="1023" /><ent r="3" t="93" w="105" /><ent r="3" t="93" w="127" /><ent r="3" t="93" w="423" /><ent r="3" t="93" w="627" /><ent r="3" t="93" w="647" /><ent r="3" t="93" w="1012" /><ent r="3" t="93" w="1352" /><ent r="3" t="93" w="1503" /><ent r="3" t="93" w="1511" /><ent r="3" t="93" w="1815" /></phr><phr n="Strain"><ent r="6" t="13" w="328" /><ent r="7" t="16" w="132" /><ent r="3" t="83" w="397" /><ent r="3" t="93" w="528" /><ent r="3" t="93" w="886" /></phr></stem><stem n="raw"><phr n="raw"><ent r="4" t="2" w="255" /><ent r="3" t="8" w="41" /><ent r="3" t="9" w="592" /><ent r="4" t="20" w="113" /><ent r="4" t="20" w="248" /><ent r="4" t="20" w="261" /><ent r="3" t="22" w="48" /><ent r="3" t="22" w="179" /><ent r="3" t="27" w="50" /><ent r="3" t="31" w="613" /><ent r="3" t="39" w="125" /><ent r="3" t="47" w="17" /><ent r="4" t="47" w="87" /><ent r="3" t="47" w="108" /><ent r="4" t="51" w="366" /><ent r="3" t="74" w="126" /><ent r="4" t="108" w="102" /></phr></stem><stem n="-compliant"><phr n="-compliant"><ent r="4" t="2" w="259" /><ent r="4" t="2" w="259" /><ent r="7" t="2" w="434" /><ent r="7" t="2" w="434" /><ent r="3" t="13" w="93" /><ent r="3" t="13" w="93" /><ent r="3" t="89" w="75" /><ent r="3" t="89" w="75" /><ent r="4" t="108" w="106" /><ent r="4" t="108" w="106" /></phr></stem><stem n="miam"><phr n="MIAME"><ent r="4" t="2" w="259" /><ent r="7" t="2" w="434" /><ent r="65" t="11" w="1086" /><ent r="3" t="13" w="93" /><ent r="64" t="13" w="155" /><ent r="3" t="13" w="168" /><ent r="3" t="89" w="75" /><ent r="64" t="90" w="31" /><ent r="1000" t="94" w="1" /><ent r="102" t="94" w="10" /><ent r="3" t="94" w="13" /><ent r="3" t="94" w="54" /><ent r="4" t="94" w="115" /><ent r="4" t="94" w="185" /><ent r="3" t="94" w="208" /><ent r="3" t="94" w="238" /><ent r="3" t="94" w="250" /><ent r="3" t="94" w="268" /><ent r="3" t="94" w="299" /><ent r="3" t="94" w="335" /><ent r="64" t="94" w="452" /><ent r="4" t="108" w="106" /></phr><phr n="miame"><ent r="64" t="94" w="453" /></phr></stem><stem n="miame-compli"><phr n="MIAME-compliant"><ent r="4" t="2" w="259" /><ent r="7" t="2" w="434" /><ent r="3" t="13" w="93" /><ent r="3" t="89" w="75" /><ent r="4" t="108" w="106" /></phr></stem><stem n="compliant"><phr n="compliant"><ent r="4" t="2" w="260" /><ent r="7" t="2" w="435" /><ent r="3" t="13" w="94" /><ent r="3" t="89" w="76" /><ent r="4" t="108" w="107" /></phr></stem><stem n="databas"><phr n="database"><ent r="4" t="2" w="261" /><ent r="7" t="2" w="436" /><ent r="3" t="3" w="93" /><ent r="3" t="13" w="95" /><ent r="4" t="13" w="137" /><ent r="4" t="13" w="463" /><ent r="3" t="33" w="53" /><ent r="3" t="57" w="229" /><ent r="3" t="57" w="235" /><ent r="3" t="57" w="250" /><ent r="3" t="57" w="670" /><ent r="3" t="57" w="681" /><ent r="3" t="58" w="300" /><ent r="4" t="59" w="133" /><ent r="4" t="59" w="154" /><ent r="4" t="59" w="170" /><ent r="4" t="59" w="179" /><ent r="4" t="64" w="267" /><ent r="4" t="64" w="282" /><ent r="4" t="76" w="203" /><ent r="3" t="89" w="249" /><ent r="3" t="106" w="39" /><ent r="4" t="108" w="108" /></phr><phr n="databases"><ent r="4" t="2" w="289" /><ent r="64" t="9" w="2168" /><ent r="3" t="57" w="224" /><ent r="3" t="57" w="309" /><ent r="3" t="57" w="854" /><ent r="3" t="57" w="881" /><ent r="3" t="58" w="266" /><ent r="3" t="75" w="45" /><ent r="64" t="93" w="1573" /><ent r="4" t="94" w="170" /><ent r="3" t="94" w="276" /><ent r="3" t="106" w="87" /><ent r="4" t="108" w="132" /><ent r="4" t="108" w="135" /></phr><phr n="Database"><ent r="5" t="58" w="120" /></phr><phr n="Databases"><ent r="4" t="76" w="172" /></phr></stem><stem n="around"><phr n="around"><ent r="4" t="2" w="272" /><ent r="4" t="18" w="211" /><ent r="3" t="19" w="251" /><ent r="3" t="19" w="328" /><ent r="3" t="22" w="137" /><ent r="3" t="26" w="53" /><ent r="3" t="64" w="299" /></phr></stem><stem n="world"><phr n="world"><ent r="4" t="2" w="274" /></phr></stem><stem n="save"><phr n="save"><ent r="4" t="2" w="279" /><ent r="4" t="8" w="125" /><ent r="3" t="9" w="154" /><ent r="4" t="9" w="403" /><ent r="3" t="10" w="42" /><ent r="4" t="11" w="450" /><ent r="4" t="11" w="458" /><ent r="3" t="15" w="410" /><ent r="3" t="43" w="1081" /><ent r="3" t="43" w="1182" /><ent r="4" t="43" w="1219" /><ent r="3" t="44" w="392" /><ent r="3" t="45" w="29" /><ent r="3" t="46" w="37" /><ent r="4" t="47" w="154" /><ent r="5" t="49" w="396" /><ent r="5" t="49" w="416" /><ent r="4" t="51" w="464" /><ent r="4" t="60" w="636" /><ent r="3" t="76" w="53" /><ent r="4" t="76" w="120" /><ent r="4" t="77" w="277" /><ent r="4" t="78" w="149" /><ent r="4" t="84" w="117" /><ent r="4" t="106" w="152" /><ent r="65" t="112" w="91" /></phr><phr n="Save"><ent r="9" t="2" w="520" /><ent r="4" t="11" w="753" /><ent r="4" t="33" w="251" /><ent r="5" t="43" w="1137" /><ent r="5" t="43" w="1215" /><ent r="5" t="44" w="269" /><ent r="5" t="44" w="371" /><ent r="5" t="44" w="477" /><ent r="5" t="44" w="596" /><ent r="5" t="45" w="52" /><ent r="5" t="51" w="458" /><ent r="5" t="60" w="630" /><ent r="5" t="76" w="130" /><ent r="5" t="76" w="136" /><ent r="5" t="76" w="183" /><ent r="5" t="77" w="269" /><ent r="5" t="82" w="192" /></phr><phr n="saved"><ent r="4" t="8" w="115" /><ent r="4" t="9" w="303" /><ent r="4" t="31" w="250" /><ent r="4" t="32" w="514" /><ent r="4" t="43" w="1145" /><ent r="4" t="76" w="192" /></phr><phr n="Saved"><ent r="5" t="9" w="388" /></phr><phr n="saves"><ent r="4" t="11" w="461" /></phr><phr n="Saving"><ent r="4" t="33" w="144" /><ent r="64" t="43" w="1186" /><ent r="1000" t="45" w="1" /><ent r="100" t="45" w="5" /><ent r="100" t="45" w="11" /><ent r="102" t="45" w="17" /><ent r="64" t="46" w="40" /><ent r="64" t="51" w="563" /><ent r="64" t="53" w="90" /><ent r="64" t="54" w="224" /><ent r="64" t="55" w="404" /><ent r="64" t="56" w="180" /><ent r="1000" t="76" w="1" /><ent r="100" t="76" w="9" /><ent r="100" t="76" w="19" /><ent r="102" t="76" w="43" /></phr></stem><stem n="translat"><phr n="Translate"><ent r="4" t="2" w="282" /><ent r="4" t="108" w="125" /></phr><phr n="translated"><ent r="4" t="51" w="467" /><ent r="3" t="57" w="35" /></phr><phr n="translates"><ent r="3" t="57" w="43" /><ent r="3" t="57" w="194" /></phr><phr n="translate"><ent r="3" t="57" w="109" /></phr></stem><stem n="multipl"><phr n="multiple"><ent r="4" t="2" w="288" /><ent r="9" t="2" w="516" /><ent r="4" t="9" w="289" /><ent r="3" t="9" w="709" /><ent r="3" t="9" w="899" /><ent r="3" t="9" w="1419" /><ent r="3" t="9" w="2068" /><ent r="3" t="13" w="180" /><ent r="3" t="13" w="183" /><ent r="3" t="18" w="580" /><ent r="3" t="20" w="520" /><ent r="3" t="31" w="111" /><ent r="3" t="31" w="117" /><ent r="3" t="31" w="2570" /><ent r="3" t="36" w="734" /><ent r="4" t="36" w="816" /><ent r="3" t="39" w="1387" /><ent r="3" t="41" w="44" /><ent r="3" t="41" w="117" /><ent r="3" t="41" w="141" /><ent r="4" t="41" w="254" /><ent r="3" t="41" w="274" /><ent r="3" t="41" w="476" /><ent r="4" t="43" w="886" /><ent r="6" t="43" w="971" /><ent r="4" t="43" w="1037" /><ent r="6" t="55" w="295" /><ent r="5" t="58" w="197" /><ent r="3" t="75" w="44" /><ent r="3" t="83" w="815" /><ent r="3" t="93" w="162" /><ent r="3" t="93" w="167" /><ent r="3" t="93" w="175" /><ent r="3" t="93" w="186" /><ent r="3" t="93" w="267" /><ent r="3" t="93" w="732" /><ent r="3" t="93" w="1473" /><ent r="4" t="93" w="1983" /><ent r="6" t="95" w="289" /><ent r="6" t="95" w="1373" /><ent r="4" t="95" w="1581" /><ent r="4" t="95" w="1604" /><ent r="4" t="108" w="131" /><ent r="4" t="108" w="162" /></phr><phr n="Multiple"><ent r="1000" t="41" w="1" /><ent r="100" t="41" w="11" /><ent r="100" t="41" w="15" /><ent r="100" t="41" w="21" /><ent r="100" t="41" w="27" /><ent r="102" t="41" w="31" /><ent r="3" t="41" w="46" /><ent r="3" t="41" w="199" /><ent r="5" t="43" w="923" /><ent r="65" t="43" w="931" /><ent r="3" t="64" w="980" /><ent r="5" t="75" w="748" /></phr></stem><stem n="determin"><phr n="Determine"><ent r="4" t="2" w="291" /></phr><phr n="determine"><ent r="4" t="13" w="32" /><ent r="4" t="14" w="86" /><ent r="3" t="14" w="308" /><ent r="4" t="18" w="88" /><ent r="3" t="31" w="1476" /><ent r="3" t="39" w="931" /><ent r="3" t="39" w="1308" /><ent r="3" t="40" w="33" /><ent r="3" t="57" w="402" /><ent r="4" t="62" w="317" /><ent r="3" t="64" w="218" /><ent r="3" t="64" w="600" /><ent r="3" t="75" w="71" /><ent r="6" t="95" w="337" /><ent r="3" t="103" w="41" /></phr><phr n="determining"><ent r="3" t="16" w="266" /><ent r="3" t="35" w="166" /><ent r="4" t="42" w="260" /><ent r="3" t="64" w="137" /></phr><phr n="determined"><ent r="3" t="31" w="1223" /><ent r="3" t="35" w="61" /><ent r="3" t="35" w="319" /><ent r="3" t="39" w="1197" /><ent r="3" t="39" w="1218" /><ent r="3" t="39" w="1367" /></phr></stem><stem n="bxd"><phr n="BXD"><ent r="4" t="2" w="295" /><ent r="82" t="9" w="778" /><ent r="3" t="9" w="791" /><ent r="3" t="9" w="852" /><ent r="3" t="9" w="1003" /><ent r="82" t="9" w="1203" /><ent r="3" t="35" w="583" /><ent r="3" t="35" w="842" /><ent r="3" t="83" w="50" /><ent r="5" t="83" w="109" /><ent r="72" t="83" w="378" /><ent r="3" t="83" w="386" /><ent r="3" t="83" w="482" /><ent r="3" t="93" w="226" /><ent r="3" t="93" w="513" /><ent r="1000" t="98" w="10" /><ent r="102" t="98" w="28" /><ent r="5" t="98" w="42" /><ent r="4" t="98" w="89" /><ent r="1000" t="116" w="10" /><ent r="102" t="116" w="23" /><ent r="3" t="116" w="45" /></phr></stem><stem n="hxb"><phr n="HXB"><ent r="4" t="2" w="299" /><ent r="82" t="9" w="1638" /><ent r="3" t="9" w="1747" /><ent r="3" t="9" w="1916" /><ent r="3" t="9" w="1953" /><ent r="6" t="13" w="332" /><ent r="3" t="31" w="2683" /><ent r="3" t="35" w="684" /><ent r="3" t="35" w="889" /><ent r="3" t="35" w="925" /><ent r="3" t="36" w="1090" /><ent r="3" t="36" w="1216" /><ent r="3" t="83" w="55" /><ent r="5" t="83" w="115" /><ent r="72" t="83" w="678" /><ent r="3" t="83" w="687" /><ent r="4" t="85" w="54" /><ent r="3" t="93" w="1075" /><ent r="3" t="93" w="1417" /><ent r="3" t="93" w="1703" /><ent r="3" t="116" w="52" /></phr><phr n="HxB"><ent r="3" t="9" w="1652" /></phr></stem><stem n="/bxh"><phr n="/BXH"><ent r="4" t="2" w="300" /><ent r="82" t="9" w="1639" /><ent r="3" t="9" w="1748" /><ent r="3" t="9" w="1917" /><ent r="3" t="9" w="1954" /><ent r="3" t="31" w="2684" /><ent r="3" t="35" w="685" /><ent r="3" t="35" w="890" /><ent r="3" t="35" w="926" /><ent r="3" t="36" w="1091" /><ent r="3" t="36" w="1217" /><ent r="3" t="83" w="56" /><ent r="5" t="83" w="116" /><ent r="72" t="83" w="679" /><ent r="3" t="83" w="688" /><ent r="4" t="85" w="55" /><ent r="3" t="93" w="1076" /><ent r="3" t="93" w="1418" /><ent r="3" t="93" w="1704" /></phr><phr n="/BxH"><ent r="3" t="9" w="1653" /></phr></stem><stem n="hxb/bxh"><phr n="HXB/BXH"><ent r="4" t="2" w="300" /><ent r="4" t="2" w="299" /><ent r="82" t="9" w="1639" /><ent r="82" t="9" w="1638" /><ent r="3" t="9" w="1748" /><ent r="3" t="9" w="1747" /><ent r="3" t="9" w="1917" /><ent r="3" t="9" w="1916" /><ent r="3" t="9" w="1954" /><ent r="3" t="9" w="1953" /><ent r="3" t="31" w="2684" /><ent r="3" t="31" w="2683" /><ent r="3" t="35" w="685" /><ent r="3" t="35" w="684" /><ent r="3" t="35" w="890" /><ent r="3" t="35" w="889" /><ent r="3" t="35" w="926" /><ent r="3" t="35" w="925" /><ent r="3" t="36" w="1091" /><ent r="3" t="36" w="1090" /><ent r="3" t="36" w="1217" /><ent r="3" t="36" w="1216" /><ent r="3" t="83" w="56" /><ent r="3" t="83" w="55" /><ent r="5" t="83" w="116" /><ent r="5" t="83" w="115" /><ent r="72" t="83" w="679" /><ent r="72" t="83" w="678" /><ent r="3" t="83" w="688" /><ent r="3" t="83" w="687" /><ent r="4" t="85" w="55" /><ent r="4" t="85" w="54" /><ent r="3" t="93" w="1076" /><ent r="3" t="93" w="1075" /><ent r="3" t="93" w="1418" /><ent r="3" t="93" w="1417" /><ent r="3" t="93" w="1704" /><ent r="3" t="93" w="1703" /></phr><phr n="HxB/BxH"><ent r="3" t="9" w="1653" /><ent r="3" t="9" w="1652" /></phr></stem><stem n="bxh"><phr n="BXH"><ent r="4" t="2" w="300" /><ent r="82" t="9" w="1639" /><ent r="3" t="9" w="1748" /><ent r="3" t="9" w="1917" /><ent r="3" t="9" w="1954" /><ent r="3" t="31" w="2684" /><ent r="3" t="35" w="685" /><ent r="3" t="35" w="890" /><ent r="3" t="35" w="926" /><ent r="3" t="36" w="1091" /><ent r="3" t="36" w="1217" /><ent r="3" t="83" w="56" /><ent r="5" t="83" w="116" /><ent r="72" t="83" w="679" /><ent r="3" t="83" w="688" /><ent r="4" t="85" w="55" /><ent r="3" t="93" w="1076" /><ent r="3" t="93" w="1418" /><ent r="3" t="93" w="1704" /></phr><phr n="BxH"><ent r="3" t="9" w="1653" /></phr></stem><stem n="lx"><phr n="LXS"><ent r="4" t="2" w="305" /><ent r="82" t="9" w="1259" /><ent r="3" t="9" w="1272" /><ent r="3" t="35" w="625" /><ent r="3" t="35" w="863" /><ent r="3" t="93" w="692" /><ent r="3" t="93" w="938" /></phr><phr n="Lx"><ent r="3" t="9" w="1679" /><ent r="3" t="9" w="1684" /><ent r="3" t="9" w="2129" /><ent r="3" t="31" w="2690" /><ent r="3" t="83" w="718" /><ent r="3" t="93" w="1534" /></phr></stem><stem n="match"><phr n="Match"><ent r="4" t="2" w="310" /><ent r="62" t="31" w="1073" /><ent r="72" t="64" w="488" /><ent r="6" t="65" w="162" /><ent r="4" t="108" w="141" /></phr><phr n="match"><ent r="3" t="9" w="699" /><ent r="3" t="9" w="889" /><ent r="3" t="9" w="1403" /><ent r="3" t="9" w="1436" /><ent r="3" t="9" w="2051" /><ent r="3" t="9" w="2085" /><ent r="4" t="13" w="487" /><ent r="4" t="14" w="113" /><ent r="4" t="14" w="254" /><ent r="3" t="14" w="279" /><ent r="3" t="31" w="681" /><ent r="4" t="31" w="1143" /><ent r="3" t="31" w="1410" /><ent r="3" t="31" w="2545" /><ent r="3" t="44" w="205" /><ent r="4" t="44" w="301" /><ent r="3" t="93" w="251" /><ent r="3" t="93" w="284" /><ent r="3" t="93" w="716" /><ent r="3" t="93" w="749" /><ent r="3" t="93" w="1456" /><ent r="3" t="93" w="1490" /></phr><phr n="matched"><ent r="3" t="9" w="705" /><ent r="3" t="9" w="895" /><ent r="3" t="9" w="1418" /><ent r="3" t="9" w="2067" /><ent r="3" t="31" w="2566" /><ent r="3" t="83" w="418" /><ent r="3" t="93" w="266" /><ent r="3" t="93" w="731" /><ent r="3" t="93" w="1472" /></phr><phr n="matching"><ent r="4" t="44" w="282" /></phr><phr n="matches"><ent r="3" t="57" w="365" /><ent r="4" t="89" w="213" /></phr></stem><stem n="physic"><phr n="physical"><ent r="4" t="2" w="311" /><ent r="4" t="51" w="247" /><ent r="3" t="57" w="485" /><ent r="3" t="57" w="531" /><ent r="3" t="57" w="561" /><ent r="3" t="60" w="63" /><ent r="5" t="60" w="252" /><ent r="6" t="60" w="690" /><ent r="5" t="60" w="701" /><ent r="4" t="81" w="131" /><ent r="4" t="99" w="135" /><ent r="3" t="100" w="27" /><ent r="5" t="100" w="100" /><ent r="3" t="101" w="27" /><ent r="5" t="101" w="103" /><ent r="4" t="101" w="212" /><ent r="3" t="102" w="41" /><ent r="1000" t="105" w="13" /><ent r="102" t="105" w="34" /><ent r="4" t="105" w="146" /><ent r="4" t="108" w="142" /></phr><phr n="Physical"><ent r="5" t="99" w="106" /><ent r="5" t="100" w="160" /><ent r="5" t="105" w="117" /></phr><phr n="physically"><ent r="3" t="105" w="57" /></phr></stem><stem n="locat"><phr n="location"><ent r="4" t="2" w="312" /><ent r="4" t="5" w="89" /><ent r="3" t="9" w="1428" /><ent r="3" t="9" w="2077" /><ent r="4" t="11" w="466" /><ent r="3" t="35" w="967" /><ent r="3" t="36" w="1251" /><ent r="4" t="42" w="341" /><ent r="4" t="51" w="248" /><ent r="4" t="51" w="307" /><ent r="3" t="57" w="404" /><ent r="3" t="57" w="486" /><ent r="3" t="57" w="497" /><ent r="3" t="57" w="511" /><ent r="3" t="57" w="532" /><ent r="3" t="57" w="539" /><ent r="3" t="57" w="562" /><ent r="3" t="60" w="47" /><ent r="3" t="60" w="128" /><ent r="4" t="60" w="206" /><ent r="5" t="60" w="253" /><ent r="4" t="60" w="294" /><ent r="6" t="60" w="691" /><ent r="5" t="60" w="702" /><ent r="3" t="60" w="816" /><ent r="3" t="60" w="825" /><ent r="3" t="72" w="85" /><ent r="3" t="72" w="119" /><ent r="3" t="72" w="135" /><ent r="5" t="72" w="247" /><ent r="3" t="81" w="41" /><ent r="4" t="81" w="132" /><ent r="5" t="83" w="250" /><ent r="3" t="83" w="1051" /><ent r="3" t="83" w="1285" /><ent r="3" t="93" w="276" /><ent r="3" t="93" w="546" /><ent r="3" t="93" w="741" /><ent r="3" t="93" w="897" /><ent r="3" t="93" w="1482" /><ent r="5" t="99" w="107" /><ent r="4" t="99" w="136" /><ent r="3" t="100" w="28" /><ent r="3" t="100" w="35" /><ent r="5" t="100" w="101" /><ent r="5" t="100" w="161" /><ent r="3" t="101" w="28" /><ent r="3" t="101" w="35" /><ent r="5" t="101" w="104" /><ent r="1000" t="102" w="5" /><ent r="102" t="102" w="23" /><ent r="1000" t="105" w="14" /><ent r="1000" t="105" w="17" /><ent r="102" t="105" w="35" /><ent r="102" t="105" w="38" /><ent r="5" t="105" w="118" /><ent r="4" t="105" w="147" /><ent r="4" t="108" w="143" /></phr><phr n="locations"><ent r="3" t="9" w="1420" /><ent r="3" t="9" w="2069" /><ent r="3" t="42" w="788" /><ent r="3" t="42" w="792" /><ent r="4" t="51" w="252" /><ent r="100" t="60" w="17" /><ent r="3" t="60" w="64" /><ent r="3" t="60" w="75" /><ent r="3" t="60" w="86" /><ent r="4" t="60" w="390" /><ent r="6" t="60" w="712" /><ent r="5" t="60" w="726" /><ent r="3" t="72" w="101" /><ent r="3" t="93" w="268" /><ent r="3" t="93" w="733" /><ent r="3" t="93" w="1270" /><ent r="3" t="93" w="1474" /><ent r="3" t="93" w="1734" /><ent r="7" t="95" w="1445" /><ent r="5" t="100" w="108" /><ent r="5" t="101" w="111" /><ent r="4" t="101" w="213" /><ent r="3" t="102" w="42" /><ent r="3" t="102" w="54" /><ent r="5" t="105" w="213" /></phr><phr n="Location"><ent r="5" t="51" w="240" /><ent r="64" t="51" w="532" /><ent r="1000" t="60" w="2" /><ent r="100" t="60" w="13" /><ent r="100" t="60" w="25" /><ent r="100" t="60" w="33" /><ent r="100" t="60" w="37" /><ent r="102" t="60" w="42" /><ent r="5" t="60" w="213" /><ent r="5" t="60" w="218" /><ent r="5" t="60" w="299" /><ent r="65" t="81" w="142" /><ent r="5" t="82" w="130" /><ent r="65" t="99" w="78" /><ent r="3" t="100" w="69" /><ent r="65" t="100" w="85" /><ent r="3" t="101" w="72" /><ent r="65" t="101" w="88" /><ent r="64" t="102" w="78" /><ent r="65" t="105" w="95" /><ent r="65" t="105" w="201" /><ent r="64" t="115" w="38" /></phr><phr n="Locations"><ent r="100" t="60" w="9" /></phr><phr n="located"><ent r="4" t="70" w="144" /><ent r="3" t="105" w="58" /></phr><phr n="locating"><ent r="4" t="83" w="1171" /></phr></stem><stem n="interest"><phr n="interest"><ent r="4" t="2" w="316" /><ent r="4" t="2" w="378" /><ent r="3" t="3" w="100" /><ent r="3" t="35" w="657" /><ent r="3" t="35" w="822" /><ent r="4" t="36" w="55" /><ent r="3" t="36" w="1193" /><ent r="3" t="39" w="1096" /><ent r="3" t="39" w="1109" /><ent r="3" t="57" w="428" /><ent r="3" t="61" w="39" /><ent r="3" t="64" w="618" /><ent r="4" t="99" w="102" /><ent r="4" t="99" w="141" /><ent r="4" t="100" w="141" /><ent r="4" t="101" w="144" /><ent r="1000" t="104" w="15" /><ent r="102" t="104" w="31" /><ent r="64" t="104" w="41" /><ent r="4" t="105" w="113" /><ent r="4" t="105" w="152" /><ent r="3" t="105" w="184" /><ent r="4" t="105" w="241" /><ent r="4" t="105" w="277" /><ent r="4" t="108" w="147" /><ent r="4" t="108" w="213" /><ent r="4" t="110" w="15" /><ent r="4" t="111" w="15" /><ent r="4" t="112" w="33" /><ent r="4" t="117" w="22" /></phr><phr n="interested"><ent r="3" t="40" w="107" /></phr><phr n="Interest"><ent r="5" t="43" w="801" /><ent r="4" t="99" w="118" /><ent r="4" t="100" w="180" /><ent r="4" t="101" w="176" /><ent r="4" t="101" w="208" /><ent r="4" t="105" w="129" /><ent r="4" t="105" w="258" /></phr></stem></index>